{
  "/EtoroPipelineStack": [
    {
      "type": "aws:cdk:creationStack",
      "data": [
        "...jsii runtime, node internals...",
        "(no user code in 10 frames, use --stack-trace-limit to capture more)"
      ]
    }
  ],
  "/EtoroPipelineStack/BootstrapVersion": [
    {
      "type": "aws:cdk:logicalId",
      "data": "BootstrapVersion"
    },
    {
      "type": "aws:cdk:creationStack",
      "data": [
        "...aws-cdk-lib...",
        "(no user code in 10 frames, use --stack-trace-limit to capture more)"
      ]
    }
  ],
  "/EtoroPipelineStack/CheckBootstrapVersion": [
    {
      "type": "aws:cdk:logicalId",
      "data": "CheckBootstrapVersion"
    },
    {
      "type": "aws:cdk:creationStack",
      "data": [
        "...aws-cdk-lib...",
        "(no user code in 10 frames, use --stack-trace-limit to capture more)"
      ]
    }
  ],
  "/EtoroPipelineStack/EtoroBucket/Resource": [
    {
      "type": "aws:cdk:logicalId",
      "data": "EtoroBucket773D0A61"
    },
    {
      "type": "aws:cdk:creationStack",
      "data": [
        "...aws-cdk-lib, jsii runtime, node internals...",
        "(no user code in 10 frames, use --stack-trace-limit to capture more)"
      ]
    }
  ],
  "/EtoroPipelineStack/EtoroIngestFn/Resource": [
    {
      "type": "aws:cdk:logicalId",
      "data": "EtoroIngestFn25D97FD6"
    },
    {
      "type": "aws:cdk:creationStack",
      "data": [
        "...aws-cdk-lib, jsii runtime, node internals...",
        "(no user code in 10 frames, use --stack-trace-limit to capture more)"
      ]
    }
  ],
  "/EtoroPipelineStack/WeeklySchedule/Resource": [
    {
      "type": "aws:cdk:logicalId",
      "data": "WeeklySchedule60EC10E3"
    },
    {
      "type": "aws:cdk:creationStack",
      "data": [
        "...aws-cdk-lib, jsii runtime, node internals...",
        "(no user code in 10 frames, use --stack-trace-limit to capture more)"
      ]
    }
  ],
  "/EtoroPipelineStack/WeeklySchedule/AllowEventRuleEtoroPipelineStackEtoroIngestFn8DA718BF": [
    {
      "type": "aws:cdk:logicalId",
      "data": "WeeklyScheduleAllowEventRuleEtoroPipelineStackEtoroIngestFn8DA718BF8392A55B"
    },
    {
      "type": "aws:cdk:creationStack",
      "data": [
        "...aws-cdk-lib, jsii runtime...",
        "(no user code in 10 frames, use --stack-trace-limit to capture more)"
      ]
    }
  ],
  "/EtoroPipelineStack/CDKMetadata/Default": [
    {
      "type": "aws:cdk:logicalId",
      "data": "CDKMetadata"
    },
    {
      "type": "aws:cdk:creationStack",
      "data": [
        "...aws-cdk-lib, jsii runtime...",
        "(no user code in 10 frames, use --stack-trace-limit to capture more)"
      ]
    }
  ],
  "/EtoroPipelineStack/EtoroIngestFn/ServiceRole/Resource": [
    {
      "type": "aws:cdk:logicalId",
      "data": "EtoroIngestFnServiceRoleA8F40F88"
    },
    {
      "type": "aws:cdk:creationStack",
      "data": [
        "...aws-cdk-lib, jsii runtime, node internals...",
        "(no user code in 10 frames, use --stack-trace-limit to capture more)"
      ]
    }
  ],
  "/EtoroPipelineStack/EtoroIngestFn/ServiceRole/DefaultPolicy/Resource": [
    {
      "type": "aws:cdk:logicalId",
      "data": "EtoroIngestFnServiceRoleDefaultPolicy35A95911"
    },
    {
      "type": "aws:cdk:creationStack",
      "data": [
        "...aws-cdk-lib...",
        "(no user code in 10 frames, use --stack-trace-limit to capture more)"
      ]
    }
  ]
}